jinnang/__init__.py
jinnang/ai/__init__.py
jinnang/ai/llm_utils.py
jinnang/arithmetic/__init__.py
jinnang/arithmetic/arithmetic.py
jinnang/common/__init__.py
jinnang/common/collections.py
jinnang/common/decorators.py
jinnang/common/exceptions.py
jinnang/common/hash.py
jinnang/common/patterns.py
jinnang/concurrency/__init__.py
jinnang/concurrency/global_lock.py
jinnang/date/__init__.py
jinnang/date/date.py
jinnang/debug/__init__.py
jinnang/debug/debug.py
jinnang/geo/__init__.py
jinnang/geo/distance.py
jinnang/io/__init__.py
jinnang/io/file.py
jinnang/io/system.py
jinnang/media/__init__.py
jinnang/media/resolution.py
jinnang/path/__init__.py
jinnang/path/path.py
jinnang/string/__init__.py
jinnang/string/string.py
jinnang/verbosity/__init__.py
jinnang/verbosity/verbosity.py
jinnang-0.2.2.dist-info/LICENSE
jinnang-0.2.2.dist-info/METADATA
jinnang-0.2.2.dist-info/WHEEL
jinnang-0.2.2.dist-info/top_level.txt
jinnang-0.2.2.dist-info/RECORD
